keras_gtar/__init__.py
keras_gtar/callbacks.py
keras_gtar/trajectory.py
keras_gtar/version.py
keras_gtar-1.1.0.dist-info/LICENSE
keras_gtar-1.1.0.dist-info/METADATA
keras_gtar-1.1.0.dist-info/WHEEL
keras_gtar-1.1.0.dist-info/top_level.txt
keras_gtar-1.1.0.dist-info/RECORD
